wxxxxxxx/__init__.py
wxxxxxxx-1.0.0.dist-info/METADATA
wxxxxxxx-1.0.0.dist-info/WHEEL
wxxxxxxx-1.0.0.dist-info/top_level.txt
wxxxxxxx-1.0.0.dist-info/RECORD
