Metadata-Version: 2.1
Name: wxxxxxxx
Version: 1.0.0
Summary: Python SDK for Panda Server
Home-page: UNKNOWN
Author: UNKNOWN
Author-email: UNKNOWN
License: UNKNOWN
Platform: UNKNOWN
